gpt_to_chatgpt/__init__.py
gpt_to_chatgpt-0.1.4.dist-info/METADATA
gpt_to_chatgpt-0.1.4.dist-info/WHEEL
gpt_to_chatgpt-0.1.4.dist-info/licenses/LICENSE
gpt_to_chatgpt-0.1.4.dist-info/RECORD
