Metadata-Version: 2.1
Name: gpt-to-chatgpt
Version: 0.1.4
Summary: A small example package
Project-URL: Homepage, https://github.com/bramses/gpt-to-chatgpt-py
Project-URL: Bug Tracker, https://github.com/bramses/gpt-to-chatgpt-py/issues
Author-email: Bram Adams <bram+support@bramadams.dev>
License-File: LICENSE
Classifier: License :: OSI Approved :: MIT License
Classifier: Operating System :: OS Independent
Classifier: Programming Language :: Python :: 3
Requires-Python: >=3.7
